{
  "page_num": 326,
  "content": [
    {
      "type": "text",
      "img_path": "p0326_007_text.png",
      "bbox": [
        [
          286,
          306
        ],
        [
          1026,
          306
        ],
        [
          1026,
          359
        ],
        [
          286,
          359
        ]
      ],
      "score": 0.8769362568855286,
      "y_pos": 306,
      "text": "- Làm giảm tỉ trọng của bộ xương.",
      "confidence": 0.9966950740133013
    },
    {
      "type": "text",
      "img_path": "p0326_004_text.png",
      "bbox": [
        [
          164,
          394
        ],
        [
          1511,
          394
        ],
        [
          1511,
          516
        ],
        [
          164,
          516
        ]
      ],
      "score": 0.95611971616745,
      "y_pos": 394,
      "text": "- Xoang đầu, mặt còn giúp cho âm thanh tiếng nói được\nêm ấm, vang vọng và truyền cảm.",
      "confidence": 0.9943622076150143
    },
    {
      "type": "text",
      "img_path": "p0326_001_text.png",
      "bbox": [
        [
          164,
          550
        ],
        [
          1512,
          550
        ],
        [
          1512,
          945
        ],
        [
          164,
          945
        ]
      ],
      "score": 0.9820324778556824,
      "y_pos": 550,
      "text": "Khi bị chấn thương hoặc nhiễm trùng các niêm mạc\nxoang bị viêm gây ung mủ. Bế tắc sự lưu thông tân dịch, vi\ntrùng sẽ biến dần niêm mạc, tân dịch thành mủ và hoại tử.\nKhi mủ đầy đặc trong hốc xoang thì có thể chảy rỉ ra ngoài\nmũi, tất cả các xoang thuộc đầu mặt đều có thể viêm trực tiếp\nhoặc lây qua bệnh viêm mũi.",
      "confidence": 0.9988340021151373
    },
    {
      "type": "paragraph_title",
      "img_path": "p0326_005_paragraph_title.png",
      "bbox": [
        [
          164,
          975
        ],
        [
          1514,
          975
        ],
        [
          1514,
          1104
        ],
        [
          164,
          1104
        ]
      ],
      "score": 0.9382468461990356,
      "y_pos": 975,
      "text": "IV. NGUYÊN NHÂN GÂY BỆNH VÀ BIỆN CHỨNG LUẬN\nTRI",
      "confidence": 0.83912583357758
    },
    {
      "type": "text",
      "img_path": "p0326_002_text.png",
      "bbox": [
        [
          164,
          1141
        ],
        [
          1510,
          1141
        ],
        [
          1510,
          1468
        ],
        [
          164,
          1468
        ]
      ],
      "score": 0.9800525903701782,
      "y_pos": 1141,
      "text": "Gây bệnh viêm mũi và viêm xoang đành rằng là do vi\ntrùng và do thời khí (phong tà, hàn tà, thấp tà, hỏa tà) nhưng\ntheo quan điểm của triết lý đông phương và luận trị của y học\ncổ truyền thì nguyên nhân chính lại là do thận (thận không\nhoàn thành chức năng quản lý, khống chế và bảo vệ).",
      "confidence": 0.9953743395811347
    },
    {
      "type": "text",
      "img_path": "p0326_000_text.png",
      "bbox": [
        [
          163,
          1499
        ],
        [
          1510,
          1499
        ],
        [
          1510,
          1897
        ],
        [
          163,
          1897
        ]
      ],
      "score": 0.9830286502838135,
      "y_pos": 1499,
      "text": "Lý luận y học cổ truyền cho rằng: \"thận chủ cốt\" (tức là\nthận làm chủ và quản lý phụ trách về xương). Thế mà mũi và\nxoang đều được cấu tạo bằng sụn (xương non). Cho nên khi\nchức năng quản lý và bảo vệ của thân suy giảm thì các cơ\nquan bộ phận trực thuộc nó mới bị suy thoái, bị vi trùng xâm\nnhập.",
      "confidence": 0.9976024419723092
    },
    {
      "type": "text",
      "img_path": "p0326_003_text.png",
      "bbox": [
        [
          164,
          1930
        ],
        [
          1511,
          1930
        ],
        [
          1511,
          2122
        ],
        [
          164,
          2122
        ]
      ],
      "score": 0.9688790440559387,
      "y_pos": 1930,
      "text": "Bởi vậy khi chữa các bệnh cho mũi và xoang hầu hết\ncác bài thuốc đều thiết lập với cơ sở là bổ thận khu tà, giải\ncảm, tiêu viêm, bài nùng, sinh cơ. Có khi người ta chỉ cần",
      "confidence": 0.9996842392004259
    },
    {
      "type": "number",
      "img_path": "p0326_006_number.png",
      "bbox": [
        [
          173,
          2224
        ],
        [
          257,
          2224
        ],
        [
          257,
          2268
        ],
        [
          173,
          2268
        ]
      ],
      "score": 0.8789404034614563,
      "y_pos": 2224,
      "text": "",
      "confidence": 0.0
    }
  ],
  "source_image": "Đông y chuẩn đoán và luận trị_page_0326.png"
}