{
  "page_num": 103,
  "content": [
    {
      "type": "header",
      "img_path": "p0103_008_header.png",
      "bbox": [
        [
          227,
          0
        ],
        [
          751,
          0
        ],
        [
          751,
          95
        ],
        [
          227,
          95
        ]
      ],
      "score": 0.6086486577987671,
      "y_pos": 0,
      "text": "TẬP ĐOÀN Y DƯỚC BẢO LONG\nwww.baolongduong.com.vn",
      "confidence": 0.9635226765045752
    },
    {
      "type": "text",
      "img_path": "p0103_001_text.png",
      "bbox": [
        [
          222,
          304
        ],
        [
          1569,
          304
        ],
        [
          1569,
          627
        ],
        [
          222,
          627
        ]
      ],
      "score": 0.9819499850273132,
      "y_pos": 304,
      "text": "- Tra từ Đồ hình Lục thập hoa giáp: từ đại lâm mộc\nngang sang cột 1 là thìn, ty, dọc lên là Mậu kỷ. Vậy Mậu thìn\nvà Kỷ ty là đai lâm mộc nhưng lấy ngày Kỷ tị vì kỷ và ty\nthuộc âm (chứng bệnh tiêu hóa la chảy của Đại Vương thuộc\nâm).",
      "confidence": 0.9875223089611623
    },
    {
      "type": "text",
      "img_path": "p0103_003_text.png",
      "bbox": [
        [
          223,
          663
        ],
        [
          1574,
          663
        ],
        [
          1574,
          854
        ],
        [
          223,
          854
        ]
      ],
      "score": 0.969940721988678,
      "y_pos": 663,
      "text": "Đồng thời Kỷ ty của lục thập hoa giáp lại ứng với đế\nvượng của vòng trường sinh. Mặt khác mộc lai bi khắc manh\nnhất là kiếm phong kim (đầu nhọn của kiếm).",
      "confidence": 0.9981441421672425
    },
    {
      "type": "text",
      "img_path": "p0103_002_text.png",
      "bbox": [
        [
          223,
          892
        ],
        [
          1570,
          892
        ],
        [
          1570,
          1080
        ],
        [
          223,
          1080
        ]
      ],
      "score": 0.971791684627533,
      "y_pos": 892,
      "text": "- Tra theo đô hình lục thập hoa giáp. Từ kiếm phong\nkim ngang ra cột 2 là Thân dâu. Doc lên là Nhâm quý. Vây\nNhâm thân, Quý dậu thuộc kiếm phong kim.",
      "confidence": 0.9923424367836656
    },
    {
      "type": "text",
      "img_path": "p0103_005_text.png",
      "bbox": [
        [
          224,
          1116
        ],
        [
          1567,
          1116
        ],
        [
          1567,
          1233
        ],
        [
          224,
          1233
        ]
      ],
      "score": 0.9601671695709229,
      "y_pos": 1116,
      "text": "Từ đế vượng là Kỷ tị theo vòng trường sinh thì tới tử là\nnhâm thân.",
      "confidence": 0.9723536040762375
    },
    {
      "type": "formula",
      "img_path": "p0103_007_formula.png",
      "bbox": [
        [
          369,
          1267
        ],
        [
          1405,
          1267
        ],
        [
          1405,
          1592
        ],
        [
          369,
          1592
        ]
      ],
      "score": 0.7121555209159851,
      "y_pos": 1267
    },
    {
      "type": "text",
      "img_path": "p0103_000_text.png",
      "bbox": [
        [
          222,
          1628
        ],
        [
          1572,
          1628
        ],
        [
          1572,
          1958
        ],
        [
          222,
          1958
        ]
      ],
      "score": 0.9832955002784729,
      "y_pos": 1628,
      "text": "Như vậy nếu bệnh không hợp với thời khí thì sẽ nặng tới\nkịch liệt ở cung đế vượng trong vòng trường sinh và sẽ chết ở\ncung tử trong vòng trường sinh, ngược lại nếu hợp với thời khí\nthì sẽ giảm bệnh ở đế vượng và khỏi ở cung tử (tức là giảm\nbệnh ở ngày Kỷ tị và khỏi ở ngày nhâm thân).",
      "confidence": 0.9996688803220802
    },
    {
      "type": "text",
      "img_path": "p0103_004_text.png",
      "bbox": [
        [
          224,
          1990
        ],
        [
          1575,
          1990
        ],
        [
          1575,
          2182
        ],
        [
          224,
          2182
        ]
      ],
      "score": 0.9659319519996643,
      "y_pos": 1990,
      "text": "Nếu luận theo ngũ hành thì bệnh của Đại Vương là bệnh\ncảm hàn mà hàn thuộc thuộc thủy. Cái hàn tà hay thủy tà ở\nbên ngoài nhập vào làm cái chính hàn hay chính thủy hữu dư",
      "confidence": 0.9955119863828554
    },
    {
      "type": "number",
      "img_path": "p0103_006_number.png",
      "bbox": [
        [
          1535,
          2225
        ],
        [
          1610,
          2225
        ],
        [
          1610,
          2267
        ],
        [
          1535,
          2267
        ]
      ],
      "score": 0.8892410397529602,
      "y_pos": 2225,
      "text": "\n\n\n",
      "confidence": 1.0
    }
  ],
  "source_image": "Đông y chuẩn đoán và luận trị_page_0103.png"
}