{
  "page_num": 136,
  "content": [
    {
      "type": "header",
      "img_path": "p0136_004_header.png",
      "bbox": [
        [
          1606,
          142
        ],
        [
          2372,
          142
        ],
        [
          2372,
          202
        ],
        [
          1606,
          202
        ]
      ],
      "score": 0.9193127155303955,
      "y_pos": 142,
      "text": "~?\n<b>CAM NANG CHAN TRI ĐONG Y</b>",
      "confidence": 0.7585650806625683
    },
    {
      "type": "header",
      "img_path": "p0136_008_header.png",
      "bbox": [
        [
          228,
          156
        ],
        [
          906,
          156
        ],
        [
          906,
          202
        ],
        [
          228,
          202
        ]
      ],
      "score": 0.9100774526596069,
      "y_pos": 156,
      "text": "HUYÊT VI TRÊN 14 ĐƯỜNG KINH",
      "confidence": 0.6824016488831619
    },
    {
      "type": "image",
      "img_path": "p0136_001_image.png",
      "bbox": [
        [
          849,
          366
        ],
        [
          1733,
          366
        ],
        [
          1733,
          1139
        ],
        [
          849,
          1139
        ]
      ],
      "score": 0.9567575454711914,
      "y_pos": 366
    },
    {
      "type": "figure_title",
      "img_path": "p0136_009_figure_title.png",
      "bbox": [
        [
          1207,
          1208
        ],
        [
          1380,
          1208
        ],
        [
          1380,
          1251
        ],
        [
          1207,
          1251
        ]
      ],
      "score": 0.8759070038795471,
      "y_pos": 1208,
      "text": "ľ",
      "confidence": 0.3671954274177551
    },
    {
      "type": "paragraph_title",
      "img_path": "p0136_003_paragraph_title.png",
      "bbox": [
        [
          226,
          1296
        ],
        [
          475,
          1296
        ],
        [
          475,
          1340
        ],
        [
          226,
          1340
        ]
      ],
      "score": 0.9219778180122375,
      "y_pos": 1296,
      "text": "29. Qui lai",
      "confidence": 0.9168143180700449
    },
    {
      "type": "text",
      "img_path": "p0136_002_text.png",
      "bbox": [
        [
          285,
          1384
        ],
        [
          2358,
          1384
        ],
        [
          2358,
          1529
        ],
        [
          285,
          1529
        ]
      ],
      "score": 0.9540347456932068,
      "y_pos": 1384,
      "text": "Vị trí: Dưới rốn 4 thốn là huyệt <i>Trung cực</i>, từ đó sang ngang mỗi bên 2 thốn là huyệt. (H. 54)\n<b>Cách châm:</b> Châm đứng kim, sâu 1 – 2 thốn. Cứu 5 –7 mồi.",
      "confidence": 0.9855198998530803
    },
    {
      "type": "text",
      "img_path": "p0136_012_text.png",
      "bbox": [
        [
          285,
          1569
        ],
        [
          2244,
          1569
        ],
        [
          2244,
          1623
        ],
        [
          285,
          1623
        ]
      ],
      "score": 0.8561545014381409,
      "y_pos": 1569,
      "text": "<b>Chủ trị</b>: Việm tinh hoàn, việm nội mạc <i>Tử cung</i>, việm phần phụ, kinh nguyệt không đều.",
      "confidence": 0.9873879783683353
    },
    {
      "type": "text",
      "img_path": "p0136_010_text.png",
      "bbox": [
        [
          280,
          1663
        ],
        [
          2355,
          1663
        ],
        [
          2355,
          1780
        ],
        [
          280,
          1780
        ]
      ],
      "score": 0.8741786479949951,
      "y_pos": 1663,
      "text": "Tác dụng phối hợp: Với Tam âm giao trị khí hư, bạch đới; với Thái xung trị thoát vị bìu,\nviêm tinh hoàn.",
      "confidence": 0.9919836084632313
    },
    {
      "type": "image",
      "img_path": "p0136_000_image.png",
      "bbox": [
        [
          904,
          1854
        ],
        [
          1663,
          1854
        ],
        [
          1663,
          2440
        ],
        [
          904,
          2440
        ]
      ],
      "score": 0.962450385093689,
      "y_pos": 1854
    },
    {
      "type": "figure_title",
      "img_path": "p0136_011_figure_title.png",
      "bbox": [
        [
          1206,
          2538
        ],
        [
          1380,
          2538
        ],
        [
          1380,
          2582
        ],
        [
          1206,
          2582
        ]
      ],
      "score": 0.8663057088851929,
      "y_pos": 2538,
      "text": "ınn    Л\n",
      "confidence": 0.8187742729981741
    },
    {
      "type": "paragraph_title",
      "img_path": "p0136_006_paragraph_title.png",
      "bbox": [
        [
          227,
          2624
        ],
        [
          534,
          2624
        ],
        [
          534,
          2675
        ],
        [
          227,
          2675
        ]
      ],
      "score": 0.9148913621902466,
      "y_pos": 2624,
      "text": "30. Khí xung",
      "confidence": 0.9275544158049992
    },
    {
      "type": "text",
      "img_path": "p0136_014_text.png",
      "bbox": [
        [
          284,
          2713
        ],
        [
          2153,
          2713
        ],
        [
          2153,
          2859
        ],
        [
          284,
          2859
        ]
      ],
      "score": 0.841657280921936,
      "y_pos": 2713,
      "text": "Vị trí: Dưới rốn 5 thốn là Khúc cốt, từ đó sang ngang mỗi bên 2 thốn là huyệt. (h54)\nCách châm: Châm đứng kim, sâu 1 đến 2 thốn. Cứu 5 mồi.",
      "confidence": 0.9898440756237883
    },
    {
      "type": "text",
      "img_path": "p0136_005_text.png",
      "bbox": [
        [
          286,
          2900
        ],
        [
          1043,
          2900
        ],
        [
          1043,
          2951
        ],
        [
          286,
          2951
        ]
      ],
      "score": 0.9191582798957825,
      "y_pos": 2900,
      "text": "Chủ trị: Bệnh ở bộ máy sinh dục.",
      "confidence": 0.9825471324079177
    },
    {
      "type": "footer",
      "img_path": "p0136_007_footer.png",
      "bbox": [
        [
          228,
          3334
        ],
        [
          1432,
          3334
        ],
        [
          1432,
          3387
        ],
        [
          228,
          3387
        ]
      ],
      "score": 0.9103032350540161,
      "y_pos": 3334,
      "text": "Bản quyển: Viện Thông tin Thư viện Y học Trung ương",
      "confidence": 0.9982551729904031
    },
    {
      "type": "number",
      "img_path": "p0136_013_number.png",
      "bbox": [
        [
          2304,
          3338
        ],
        [
          2351,
          3338
        ],
        [
          2351,
          3378
        ],
        [
          2304,
          3378
        ]
      ],
      "score": 0.849808394908905,
      "y_pos": 3338,
      "text": "\n\n\n\n\n",
      "confidence": 1.0
    }
  ],
  "source_image": "CamNangChanTriDongY_LeVanSuu_page_0136.png"
}