{
  "page_num": 155,
  "content": [
    {
      "type": "paragraph_title",
      "img_path": "p0155_019_paragraph_title.png",
      "bbox": [
        [
          1075,
          530
        ],
        [
          1401,
          530
        ],
        [
          1401,
          593
        ],
        [
          1075,
          593
        ]
      ],
      "score": 0.7662366628646851,
      "y_pos": 530,
      "text": "THÂN ÂM HƯ",
      "confidence": 0.7811360557874044
    },
    {
      "type": "text",
      "img_path": "p0155_020_text.png",
      "bbox": [
        [
          463,
          711
        ],
        [
          1797,
          711
        ],
        [
          1797,
          761
        ],
        [
          463,
          761
        ]
      ],
      "score": 0.6171187162399292,
      "y_pos": 711,
      "text": "- Chức năng chủ yếu bị rối loạn là chức năng bế tàng, tàng tinh của Tỳ",
      "confidence": 0.9978360840015941
    },
    {
      "type": "text",
      "img_path": "p0155_022_text.png",
      "bbox": [
        [
          464,
          786
        ],
        [
          1884,
          786
        ],
        [
          1884,
          835
        ],
        [
          464,
          835
        ]
      ],
      "score": 0.6056973338127136,
      "y_pos": 786,
      "text": "- Chủ chứng (triệu chứng quan trọng): sụt cân, đau lưng, ù tai. Sốt về chiều",
      "confidence": 0.9995772341887156
    },
    {
      "type": "text",
      "img_path": "p0155_021_text.png",
      "bbox": [
        [
          464,
          860
        ],
        [
          1952,
          860
        ],
        [
          1952,
          910
        ],
        [
          464,
          910
        ]
      ],
      "score": 0.6135375499725342,
      "y_pos": 860,
      "text": "- Thuốc tiêu biểu trong điều trị bệnh chứng Thận âm hư: Lục vị địa hoàng hoàn",
      "confidence": 0.999747162378287
    },
    {
      "type": "paragraph_title",
      "img_path": "p0155_006_paragraph_title.png",
      "bbox": [
        [
          344,
          1041
        ],
        [
          1187,
          1041
        ],
        [
          1187,
          1092
        ],
        [
          344,
          1092
        ]
      ],
      "score": 0.936474084854126,
      "y_pos": 1041,
      "text": "2.4. Bệnh chứng Thận khí bất túc",
      "confidence": 0.9987104833126068
    },
    {
      "type": "paragraph_title",
      "img_path": "p0155_005_paragraph_title.png",
      "bbox": [
        [
          344,
          1163
        ],
        [
          816,
          1163
        ],
        [
          816,
          1212
        ],
        [
          344,
          1212
        ]
      ],
      "score": 0.9372603893280029,
      "y_pos": 1163,
      "text": "2.4.1. Bênh nguyên",
      "confidence": 0.8921599090099335
    },
    {
      "type": "text",
      "img_path": "p0155_015_text.png",
      "bbox": [
        [
          408,
          1261
        ],
        [
          1173,
          1261
        ],
        [
          1173,
          1309
        ],
        [
          408,
          1309
        ]
      ],
      "score": 0.9252985119819641,
      "y_pos": 1261,
      "text": "Do bẩm tố tiên thiên không đủ.",
      "confidence": 0.9976293183863163
    },
    {
      "type": "text",
      "img_path": "p0155_013_text.png",
      "bbox": [
        [
          408,
          1346
        ],
        [
          988,
          1346
        ],
        [
          988,
          1393
        ],
        [
          408,
          1393
        ]
      ],
      "score": 0.9269559979438782,
      "y_pos": 1346,
      "text": "Do mắc bệnh lâu ngày.",
      "confidence": 0.9921018895895585
    },
    {
      "type": "text",
      "img_path": "p0155_010_text.png",
      "bbox": [
        [
          464,
          1428
        ],
        [
          1219,
          1428
        ],
        [
          1219,
          1479
        ],
        [
          464,
          1479
        ]
      ],
      "score": 0.9319614171981812,
      "y_pos": 1428,
      "text": "Do lao tổn quá độ, lão suy gây ra.",
      "confidence": 0.9975286308262084
    },
    {
      "type": "paragraph_title",
      "img_path": "p0155_009_paragraph_title.png",
      "bbox": [
        [
          344,
          1535
        ],
        [
          745,
          1535
        ],
        [
          745,
          1582
        ],
        [
          344,
          1582
        ]
      ],
      "score": 0.9325032234191895,
      "y_pos": 1535,
      "text": "2.4.2. Bênh sinh",
      "confidence": 0.9406510260370042
    },
    {
      "type": "text",
      "img_path": "p0155_000_text.png",
      "bbox": [
        [
          411,
          1635
        ],
        [
          2125,
          1635
        ],
        [
          2125,
          1797
        ],
        [
          411,
          1797
        ]
      ],
      "score": 0.970982015132904,
      "y_pos": 1635,
      "text": "- Thận tàng tinh và chủ bế tàng. Nếu Thận khí bất túc, thì công năng này\nsẽ bị ảnh hưởng sinh chứng di, hoạt tinh, tiểu nhiều lần, tiểu không tự\nchủ (ha nguyên bất cố).",
      "confidence": 0.8994723809093483
    },
    {
      "type": "text",
      "img_path": "p0155_001_text.png",
      "bbox": [
        [
          406,
          1832
        ],
        [
          2125,
          1832
        ],
        [
          2125,
          1940
        ],
        [
          406,
          1940
        ]
      ],
      "score": 0.963813841342926,
      "y_pos": 1832,
      "text": "- \"Thân nap khí\". Thận khí bất túc, làm ảnh hưởng chức năng tuyên giáng\ncủa Phế khí gây chứng thở khó, hít vào ngắn, thở ra dài.",
      "confidence": 0.929074836308009
    },
    {
      "type": "paragraph_title",
      "img_path": "p0155_007_paragraph_title.png",
      "bbox": [
        [
          342,
          1999
        ],
        [
          1049,
          1999
        ],
        [
          1049,
          2049
        ],
        [
          342,
          2049
        ]
      ],
      "score": 0.9353947639465332,
      "y_pos": 1999,
      "text": "2.4.3. Triệu chứng lâm sàng",
      "confidence": 0.9767488158982376
    },
    {
      "type": "text",
      "img_path": "p0155_004_text.png",
      "bbox": [
        [
          406,
          2095
        ],
        [
          2123,
          2095
        ],
        [
          2123,
          2203
        ],
        [
          406,
          2203
        ]
      ],
      "score": 0.9578903913497925,
      "y_pos": 2095,
      "text": "- Người mệt mỏi, chóng mặt, tai ù, mắt kém. Thường kêu đau mỏi thắt\nlưng, thở khó, hít vào ngắn, thở ra dài...",
      "confidence": 0.9958440331700449
    },
    {
      "type": "text",
      "img_path": "p0155_003_text.png",
      "bbox": [
        [
          406,
          2237
        ],
        [
          2120,
          2237
        ],
        [
          2120,
          2344
        ],
        [
          406,
          2344
        ]
      ],
      "score": 0.96198970079422,
      "y_pos": 2237,
      "text": "- Sợ lạnh, tay chân lạnh, mồ hôi tự ra. Thường kêu bụng trướng, tiêu hóa\nrối loan, dễ tiêu chảy.",
      "confidence": 0.9962672041719024
    },
    {
      "type": "text",
      "img_path": "p0155_011_text.png",
      "bbox": [
        [
          406,
          2377
        ],
        [
          1492,
          2377
        ],
        [
          1492,
          2429
        ],
        [
          406,
          2429
        ]
      ],
      "score": 0.9294807314872742,
      "y_pos": 2377,
      "text": "- Tiểu nhiều lần, tiểu trong, tiểu không tự chủ.",
      "confidence": 0.4943667447566986
    },
    {
      "type": "text",
      "img_path": "p0155_012_text.png",
      "bbox": [
        [
          406,
          2464
        ],
        [
          1331,
          2464
        ],
        [
          1331,
          2511
        ],
        [
          406,
          2511
        ]
      ],
      "score": 0.9289447665214539,
      "y_pos": 2464,
      "text": "- Di tinh, hoat tinh, liệt dương, vô kinh.",
      "confidence": 0.3837033063173294
    },
    {
      "type": "text",
      "img_path": "p0155_014_text.png",
      "bbox": [
        [
          406,
          2545
        ],
        [
          1579,
          2545
        ],
        [
          1579,
          2596
        ],
        [
          406,
          2596
        ]
      ],
      "score": 0.9269417524337769,
      "y_pos": 2545,
      "text": "- Lưỡi bệu, rêu lưỡi trắng mỏng. Mạch trầm vô lực.",
      "confidence": 0.9638059672254783
    },
    {
      "type": "paragraph_title",
      "img_path": "p0155_008_paragraph_title.png",
      "bbox": [
        [
          343,
          2653
        ],
        [
          1222,
          2653
        ],
        [
          1222,
          2704
        ],
        [
          343,
          2704
        ]
      ],
      "score": 0.9352993369102478,
      "y_pos": 2653,
      "text": "2.4.4. Bệnh cảnh Tây y thường gặp",
      "confidence": 0.9816743220601764
    },
    {
      "type": "text",
      "img_path": "p0155_016_text.png",
      "bbox": [
        [
          407,
          2754
        ],
        [
          1201,
          2754
        ],
        [
          1201,
          2802
        ],
        [
          407,
          2802
        ]
      ],
      "score": 0.9222192764282227,
      "y_pos": 2754,
      "text": "- Suy sinh dục, di tinh, liệt dương",
      "confidence": 0.4847635248222867
    },
    {
      "type": "text",
      "img_path": "p0155_002_text.png",
      "bbox": [
        [
          407,
          2836
        ],
        [
          2122,
          2836
        ],
        [
          2122,
          2942
        ],
        [
          407,
          2942
        ]
      ],
      "score": 0.9637618064880371,
      "y_pos": 2836,
      "text": "- Suy hô hấp mạn, suy nhược cơ thể, những bệnh mạn tính có kèm suy\nnhược.",
      "confidence": 0.9569250209366573
    },
    {
      "type": "number",
      "img_path": "p0155_018_number.png",
      "bbox": [
        [
          352,
          3110
        ],
        [
          430,
          3110
        ],
        [
          430,
          3148
        ],
        [
          352,
          3148
        ]
      ],
      "score": 0.8475005030632019,
      "y_pos": 3110,
      "text": "    \n\n",
      "confidence": 1.0
    },
    {
      "type": "footer",
      "img_path": "p0155_017_footer.png",
      "bbox": [
        [
          293,
          3311
        ],
        [
          1072,
          3311
        ],
        [
          1072,
          3365
        ],
        [
          293,
          3365
        ]
      ],
      "score": 0.916656494140625,
      "y_pos": 3311,
      "text": "Copyright@Ministry Of Health - VN",
      "confidence": 0.879438819204058
    }
  ],
  "source_image": "benh-hoc-va-dieu-tri-dong-y_page_0155.png"
}